{
    "schema": "DiagAssemblyStatus_DetailLevel_Update_Schema_V1.3.2.json",
    "description": "",
    "assemblyStatus": {
        "vehicleInformation": {
            "VIN": "FLORINVEH34756090"
        },
        "assemblyInformation": [
            {
                "ecuInformation": {
                    "dataObjects": {
                        "partNumber": "85F907468  ",
                        "zdcVersion": "",
                        "fazitIdString": [
                            "BPA-08528.01.2115281234"
                        ],
                        "zdcPartNumber": "",
                        "asamFileVersion": "004030",
                        "hardwareVersion": "X09",
                        "softwareVersion": "G111",
                        "asamFileIdentifier": "EV_HCP5GatewAU416",
                        "hardwarePartNumber": "85F907468  "
                    },
                    "logicalLink": "",
                    "diagnosisAddress": "0019"
                }
            },
            {
                "ecuInformation": {
                    "dataObjects": {
                        "partNumber": "85F907468  ",
                        "zdcVersion": "",
                        "fazitIdString": [
                            "BPA-08528.01.2115281234"
                        ],
                        "zdcPartNumber": "",
                        "asamFileVersion": "004030",
                        "hardwareVersion": "X09",
                        "softwareVersion": "G111",
                        "asamFileIdentifier": "EV_HCP5GatewAU416",
                        "hardwarePartNumber": "85F907468  "
                    },
                    "logicalLink": "",
                    "diagnosisAddress": "00CA"
                }
            }
        ]
    },
    "releaseVersion": "1.0.0",
    "assemblyStatusMetaData": {
        "vcHash": "5B74068B21633B8CD9CB04C24126DD707184DB516723AEDC1227CD330EFB3492",
        "newestEntryTimestamp": "2023-09-19T13:52:17.331Z",
        "oldestEntryTimestamp": "2022-06-10T10:38:47.833Z"
    }
}