<?xml version="1.0" encoding="UTF-8"?>
<con:resource name="/api/aps_campaigns/retry/{uuid}" path="/api/aps_campaigns/retry/{uuid}" id="a3178621-f05a-41a5-b758-a537a5ffe2ef" xmlns:xsi="http://www.w3.org/2001/XMLSchema-instance" xmlns:con="http://eviware.com/soapui/config">
  <con:settings>
    <con:setting id="31334455-dda6-44de-ae09-bf3f5899793afileName">%2Fapi%2Faps_campaigns%2Fretry%2F%7Buuid%7D</con:setting>
    <con:setting id="a3178621-f05a-41a5-b758-a537a5ffe2effileName">%2Fapi%2Faps_campaigns%2Fretry%2F%7Buuid%7D</con:setting>
  </con:settings>
  <con:parameters>
    <con:parameter required="true">
      <con:name>uuid</con:name>
      <con:value/>
      <con:style>TEMPLATE</con:style>
      <con:default/>
      <con:description>uuid</con:description>
    </con:parameter>
  </con:parameters>
  <con:method name="doSingleRetry" id="e5cb1e21-9855-4320-ac9b-046dc0b16806" method="POST">
    <con:description>Execute attempt to retry operation</con:description>
    <con:settings/>
    <con:parameters/>
    <con:representation type="RESPONSE">
      <con:mediaType>*/*</con:mediaType>
      <con:status>200</con:status>
      <con:params/>
      <con:sampleContent xsi:nil="true"/>
    </con:representation>
    <con:representation type="RESPONSE">
      <con:mediaType>*/*</con:mediaType>
      <con:status>201</con:status>
      <con:params/>
    </con:representation>
    <con:representation type="RESPONSE">
      <con:mediaType>*/*</con:mediaType>
      <con:status>401</con:status>
      <con:params/>
    </con:representation>
    <con:representation type="RESPONSE">
      <con:mediaType>*/*</con:mediaType>
      <con:status>403</con:status>
      <con:params/>
    </con:representation>
    <con:representation type="RESPONSE">
      <con:mediaType>*/*</con:mediaType>
      <con:status>404</con:status>
      <con:params/>
    </con:representation>
    <con:representation type="REQUEST">
      <con:mediaType>application/json</con:mediaType>
      <con:params/>
    </con:representation>
    <con:request name="Request 1" id="76aca71a-5798-423c-8fdb-4573de3dc9f2" mediaType="application/json">
      <con:settings/>
      <con:endpoint>https://demo.orunext.com</con:endpoint>
      <con:request/>
      <con:credentials>
        <con:selectedAuthProfile>No Authorization</con:selectedAuthProfile>
        <con:authType>No Authorization</con:authType>
      </con:credentials>
      <con:jmsConfig JMSDeliveryMode="PERSISTENT"/>
      <con:parameters>
        <con:entry key="uuid" value=""/>
      </con:parameters>
      <con:environmentSpec>
        <con:entry environmentId="4f515789-2a71-4da6-9bbc-0aff4cd795fa">
          <con:authProfile>Inherit From Parent</con:authProfile>
        </con:entry>
        <con:entry environmentId="19d15dbe-9720-4a73-b417-71308b8db01e">
          <con:authProfile>No Authorization</con:authProfile>
        </con:entry>
      </con:environmentSpec>
    </con:request>
    <con:environmentSpec>
      <con:entry environmentId="19d15dbe-9720-4a73-b417-71308b8db01e">
        <con:authProfile>Inherit From Parent</con:authProfile>
      </con:entry>
    </con:environmentSpec>
  </con:method>
  <con:environmentSpec>
    <con:entry environmentId="19d15dbe-9720-4a73-b417-71308b8db01e">
      <con:authProfile>Inherit From Parent</con:authProfile>
    </con:entry>
  </con:environmentSpec>
</con:resource>
